modrs-0.4.0_beta.dist-info/METADATA
modrs-0.4.0_beta.dist-info/WHEEL
modrs-0.4.0_beta.dist-info/entry_points.txt
modrs/__init__.py
modrs/modrs.pyd
modrs-0.4.0_beta.dist-info/RECORD
